{
"meta":{"test_sets":[],"test_metrics":[],"learn_metrics":[{"best_value":"Min","name":"Logloss"}],"launch_mode":"Train","parameters":"","iteration_count":10,"learn_sets":["learn"],"name":"experiment"},
"iterations":[
{"learn":[0.6587032685],"iteration":0,"passed_time":0.0023413196,"remaining_time":0.0210718764},
{"learn":[0.5978706341],"iteration":1,"passed_time":0.004084668796,"remaining_time":0.01633867518},
{"learn":[0.569151432],"iteration":2,"passed_time":0.005751411526,"remaining_time":0.01341996023},
{"learn":[0.5448033214],"iteration":3,"passed_time":0.007357252864,"remaining_time":0.0110358793},
{"learn":[0.5282327238],"iteration":4,"passed_time":0.008954712434,"remaining_time":0.008954712434},
{"learn":[0.5160084799],"iteration":5,"passed_time":0.0105856845,"remaining_time":0.007057123003},
{"learn":[0.4983407597],"iteration":6,"passed_time":0.01226263845,"remaining_time":0.005255416478},
{"learn":[0.4702844889],"iteration":7,"passed_time":0.01406839129,"remaining_time":0.003517097823},
{"learn":[0.4423390801],"iteration":8,"passed_time":0.01599334096,"remaining_time":0.001777037885},
{"learn":[0.4182046187],"iteration":9,"passed_time":0.01766841018,"remaining_time":0}
]}